{
  "tests": [
   { 
      "name": "Test 1",
      "setup": "javac ArraysExam.java",
      "run": "java ArraysExam",
      "input": "5\r\n8\r\n2\r\n7\r\n6\r\n1\r\n5\r\n6\r\n3\r\n5\r\n1\r\n8",
      "output": "Number of values greater than 7: 1\\nNumber of values less than 7: 3\\n8 2 7 6 1( )?(.|\\n)*Sum of odd values: 9\\nSum of values at even indexes: 19\\n6 3 5 1 8( )?$",
      "comparison": "regex",
      "timeout": 10,
      "points": null
    },
    { 
      "name": "Test 2",
      "setup": "javac ArraysExam.java",
      "run": "java ArraysExam",
      "input": "1\r\n7\r\n3\r\n4\r\n1\r\n4",
      "output": "Number of values greater than 7: 0\\nNumber of values less than 7: 0\\n7( )?(.|\\n)*Sum of odd values: 1\\nSum of values at even indexes: 8\\n4 1 4( )?$",
      "comparison": "regex",
      "timeout": 10,
      "points": null
    },
    { 
      "name": "Test 3",
      "setup": "javac ArraysExam.java",
      "run": "java ArraysExam",
      "input": "4\r\n1\r\n11\r\n10\r\n13\r\n1\r\n7",
      "output": "Number of values greater than 7: 3\\nNumber of values less than 7: 1\\n1 11 10 13( )?(.|\\n)*Sum of odd values: 7\\nSum of values at even indexes: 7\\n7( )?$",
      "comparison": "regex",
      "timeout": 10,
      "points": null
    }
  ]
}
